maskify/__init__.py
maskify/main.py
maskify-0.1.0.dist-info/licenses/LICENSE
maskify-0.1.0.dist-info/METADATA
maskify-0.1.0.dist-info/WHEEL
maskify-0.1.0.dist-info/top_level.txt
maskify-0.1.0.dist-info/RECORD
