Metadata-Version: 2.4
Name: maskify
Version: 0.1.0
Summary: A simple tool to mask sensitive columns in .csv and .dat files.
Author: Vikas Bhaskar Vooradi
Author-email: vikasvooradi.developer@gmail.com
License: MIT
Classifier: Programming Language :: Python :: 3
Classifier: Operating System :: OS Independent
Classifier: License :: OSI Approved :: MIT License
Requires-Python: >=3.12.11
License-File: LICENSE
Requires-Dist: polars>=1.25.2
Dynamic: author
Dynamic: author-email
Dynamic: classifier
Dynamic: description
Dynamic: description-content-type
Dynamic: license
Dynamic: license-file
Dynamic: requires-dist
Dynamic: requires-python
Dynamic: summary
